instagram_bucketizer/__init__.py
instagram_bucketizer/__main__.py
instagram_bucketizer/app.py
instagram_bucketizer/dev_requirements.txt
instagram_bucketizer/entry.py
instagram_bucketizer/py.typed
instagram_bucketizer/requirements.txt
instagram_bucketizer/buckets/__init__.py
instagram_bucketizer/buckets/bucketizer.py
instagram_bucketizer/buckets/emoji_tone.py
instagram_bucketizer/commands/__init__.py
instagram_bucketizer/commands/all.py
instagram_bucketizer/commands/bucketize.py
instagram_bucketizer/commands/parse_post.py
instagram_bucketizer/commands/setup_session.py
instagram_bucketizer-0.1.0.dist-info/LICENSE
instagram_bucketizer-0.1.0.dist-info/METADATA
instagram_bucketizer-0.1.0.dist-info/WHEEL
instagram_bucketizer-0.1.0.dist-info/entry_points.txt
instagram_bucketizer-0.1.0.dist-info/top_level.txt
instagram_bucketizer-0.1.0.dist-info/RECORD
