Metadata-Version: 2.1
Name: instagram-bucketizer
Version: 0.1.0
Summary: Small project to assist in research, categorizing instagram emoji usage
Home-page: https://github.com/dylanfromm/instagram-bucketizer
Author: Dylan Fromm
Author-email: Dylan Fromm <dylanfromm@hotmail.com>
Maintainer-email: Dylan Fromm <dylanfromm@hotmail.com>
Classifier: Programming Language :: Python :: 3.8
Classifier: Programming Language :: Python :: 3.9
Classifier: Programming Language :: Python :: 3.10
Classifier: Programming Language :: Python :: 3.11
Classifier: Operating System :: Microsoft :: Windows
Classifier: Operating System :: MacOS
Classifier: Operating System :: POSIX :: Linux
Classifier: Operating System :: Unix
Classifier: Development Status :: 5 - Production/Stable
Classifier: License :: OSI Approved :: MIT License
Requires-Python: >=3.8
License-File: LICENSE
Requires-Dist: pandas
Requires-Dist: emoji
Requires-Dist: vcorelib
Requires-Dist: tdqm
Requires-Dist: instaloader
Requires-Dist: openpyxl
Provides-Extra: test
Requires-Dist: pylint ; extra == 'test'
Requires-Dist: flake8 ; extra == 'test'
Requires-Dist: black ; extra == 'test'
Requires-Dist: ruff ; extra == 'test'
Requires-Dist: mypy ; extra == 'test'
Requires-Dist: isort ; extra == 'test'
Requires-Dist: yamllint ; extra == 'test'
Requires-Dist: yambs ; extra == 'test'
Requires-Dist: vmklib ; extra == 'test'
Requires-Dist: sphinx ; extra == 'test'
Requires-Dist: sphinx-book-theme ; extra == 'test'
Requires-Dist: setuptools-wrapper ; extra == 'test'
Requires-Dist: types-setuptools ; extra == 'test'
